ovos_skill_screenshot/LICENSE
ovos_skill_screenshot/MANIFEST.in
ovos_skill_screenshot/README.md
ovos_skill_screenshot/__init__.py
ovos_skill_screenshot/requirements.txt
ovos_skill_screenshot/version.py
ovos_skill_screenshot/locale/ca-es/screenshot.failed.dialog
ovos_skill_screenshot/locale/ca-es/screenshot.taken.dialog
ovos_skill_screenshot/locale/ca-es/skill.json
ovos_skill_screenshot/locale/ca-es/take.screenshot.intent
ovos_skill_screenshot/locale/da-dk/take.screenshot.intent
ovos_skill_screenshot/locale/de-de/screenshot.failed.dialog
ovos_skill_screenshot/locale/de-de/screenshot.taken.dialog
ovos_skill_screenshot/locale/de-de/skill.json
ovos_skill_screenshot/locale/de-de/take.screenshot.intent
ovos_skill_screenshot/locale/en-us/screenshot.failed.dialog
ovos_skill_screenshot/locale/en-us/screenshot.taken.dialog
ovos_skill_screenshot/locale/en-us/skill.json
ovos_skill_screenshot/locale/en-us/take.screenshot.intent
ovos_skill_screenshot/locale/es-es/take.screenshot.intent
ovos_skill_screenshot/locale/eu/take.screenshot.intent
ovos_skill_screenshot/locale/fr-fr/take.screenshot.intent
ovos_skill_screenshot/locale/gl-es/take.screenshot.intent
ovos_skill_screenshot/locale/it-it/take.screenshot.intent
ovos_skill_screenshot/locale/nl-nl/take.screenshot.intent
ovos_skill_screenshot/locale/pt-PT/skill.json
ovos_skill_screenshot/locale/pt-pt/screenshot.failed.dialog
ovos_skill_screenshot/locale/pt-pt/screenshot.taken.dialog
ovos_skill_screenshot/locale/pt-pt/take.screenshot.intent
ovos_skill_screenshot/ovos_skill_screenshot.egg-info/PKG-INFO
ovos_skill_screenshot/ovos_skill_screenshot.egg-info/SOURCES.txt
ovos_skill_screenshot/ovos_skill_screenshot.egg-info/dependency_links.txt
ovos_skill_screenshot/ovos_skill_screenshot.egg-info/entry_points.txt
ovos_skill_screenshot/ovos_skill_screenshot.egg-info/requires.txt
ovos_skill_screenshot/ovos_skill_screenshot.egg-info/top_level.txt
ovos_skill_screenshot-0.0.7.dist-info/LICENSE
ovos_skill_screenshot-0.0.7.dist-info/METADATA
ovos_skill_screenshot-0.0.7.dist-info/WHEEL
ovos_skill_screenshot-0.0.7.dist-info/entry_points.txt
ovos_skill_screenshot-0.0.7.dist-info/top_level.txt
ovos_skill_screenshot-0.0.7.dist-info/RECORD
