Metadata-Version: 2.1
Name: ovos-skill-screenshot
Version: 0.0.7
Summary: OVOS screenshot skill plugin
Home-page: https://github.com/OpenVoiceOS/ovos-skill-screenshot
Author: jarbasAi
License: Apache-2.0
Keywords: ovos skill plugin
License-File: LICENSE
Requires-Dist: mss
Requires-Dist: ovos-workshop
